softmatcha/__init__.py
softmatcha/configs.py
softmatcha/configs_test.py
softmatcha/conftest.py
softmatcha/functional.py
softmatcha/functional_test.py
softmatcha/registry.py
softmatcha/registry_test.py
softmatcha/stopwatch.py
softmatcha/stopwatch_test.py
softmatcha/typing.py
softmatcha/cli/__init__.py
softmatcha/cli/build_inverted_index.py
softmatcha/cli/grep.py
softmatcha/cli/search_inverted_index.py
softmatcha/embeddings/__init__.py
softmatcha/embeddings/base.py
softmatcha/embeddings/fasttext.py
softmatcha/embeddings/gensim.py
softmatcha/embeddings/gensim_test.py
softmatcha/embeddings/transformers.py
softmatcha/embeddings/transformers_test.py
softmatcha/search/__init__.py
softmatcha/search/base.py
softmatcha/search/index_inverted.py
softmatcha/search/index_inverted_test.py
softmatcha/search/naive.py
softmatcha/search/naive_test.py
softmatcha/search/quick.py
softmatcha/search/quick_test.py
softmatcha/struct/__init__.py
softmatcha/struct/index.py
softmatcha/struct/index_inverted.py
softmatcha/struct/index_inverted_test.py
softmatcha/struct/index_test.py
softmatcha/struct/pattern.py
softmatcha/struct/sparse_matrix.py
softmatcha/struct/sparse_matrix_test.py
softmatcha/struct/token_embeddings.py
softmatcha/tokenizers/__init__.py
softmatcha/tokenizers/base.py
softmatcha/tokenizers/fasttext.py
softmatcha/tokenizers/gensim.py
softmatcha/tokenizers/icu.py
softmatcha/tokenizers/icu_test.py
softmatcha/tokenizers/mecab.py
softmatcha/tokenizers/mecab_test.py
softmatcha/tokenizers/moses.py
softmatcha/tokenizers/moses_test.py
softmatcha/tokenizers/transformers.py
softmatcha/tokenizers/transformers_test.py
softmatcha/utils/__init__.py
softmatcha/utils/fasttext.py
softmatcha/utils/gensim.py
softmatcha/utils/io.py
softmatcha-0.1.0.dist-info/METADATA
softmatcha-0.1.0.dist-info/WHEEL
softmatcha-0.1.0.dist-info/entry_points.txt
softmatcha-0.1.0.dist-info/licenses/LICENSE
softmatcha-0.1.0.dist-info/RECORD
