Metadata-Version: 2.4
Name: softmatcha
Version: 0.1.0
Summary: SoftMatcha
Author-email: Hiroyuki Deguchi <deguchi.hiroyuki.db0@is.naist.jp>
License-File: LICENSE
Requires-Python: >=3.10
Requires-Dist: fasttext>=0.9.3
Requires-Dist: gensim>=4.3.3
Requires-Dist: h5py>=3.12.1
Requires-Dist: icu-tokenizer>=0.0.1
Requires-Dist: ipadic>=1.0.0
Requires-Dist: mecab-python3>=1.0.10
Requires-Dist: numba>=0.60.0
Requires-Dist: numpy>=1.26.4
Requires-Dist: pysimdjson>=6.0.2
Requires-Dist: sacremoses>=0.1.1
Requires-Dist: simple-parsing>=0.1.6
Requires-Dist: termcolor>=2.5.0
Requires-Dist: torch>=2.5.1
Requires-Dist: transformers>=4.47.0
